[{"event":"IEM Cologne 2021 Play-In","time":"2021-07-08 05:36:56","team1":{"name":"Spirit","result":2},"team2":{"name":"Sprout","result":1},"matchId":"2349709","maxround":30},{"event":"IEM Cologne 2021 Play-In","time":"2021-07-08 00:46:04","team1":{"name":"LDLC","result":0},"team2":{"name":"Complexity","result":2},"matchId":"2349707","maxround":29},{"event":"IEM Cologne 2021 Play-In","time":"2021-07-07 05:55:49","team1":{"name":"BIG","result":2},"team2":{"name":"OG","result":0},"matchId":"2349701","maxround":25},{"event":"IEM Cologne 2021 Play-In","time":"2021-07-07 04:08:35","team1":{"name":"FaZe","result":2},"team2":{"name":"Complexity","result":0},"matchId":"2349702","maxround":29},{"event":"IEM Cologne 2021 Play-In","time":"2021-07-07 02:45:16","team1":{"name":"Spirit","result":1},"team2":{"name":"Vitality","result":2},"matchId":"2349700","maxround":30},{"event":"StarLadder CIS RMR 2021","time":"2021-07-05 05:40:30","team1":{"name":"Gambit","result":2},"team2":{"name":"Natus Vincere","result":3},"matchId":"2349632","maxround":25},{"event":"StarLadder CIS RMR 2021","time":"2021-07-05 00:11:39","team1":{"name":"Spirit","result":1},"team2":{"name":"Natus Vincere","result":2},"matchId":"2349631","maxround":25},{"event":"StarLadder CIS RMR 2021","time":"2021-07-04 05:32:40","team1":{"name":"Gambit","result":2},"team2":{"name":"Natus Vincere","result":1},"matchId":"2349630","maxround":24},{"event":"StarLadder CIS RMR 2021","time":"2021-07-04 01:29:35","team1":{"name":"K23","result":1},"team2":{"name":"Spirit","result":2},"matchId":"2349629","maxround":26},{"event":"Pinnacle Cup II","time":"2021-07-03 00:43:55","team1":{"name":"HAVU","result":1},"team2":{"name":"MIBR","result":2},"matchId":"2349783","maxround":19}]