[{"event":"DreamHack Open November 2021 Closed Qualifier","time":"2021-10-22 04:43:20","team1":{"name":"forZe","result":1},"team2":{"name":"GamerLegion","result":2},"matchId":"2352549","maxround":12},{"event":"DreamHack Open November 2021 Closed Qualifier","time":"2021-10-21 01:48:53","team1":{"name":"Eternal Fire","result":0},"team2":{"name":"forZe","result":2},"matchId":"2352535","maxround":20},{"event":"IEM Winter 2021 Europe Closed Qualifier","time":"2021-10-19 22:31:23","team1":{"name":"FunPlus Phoenix","result":2},"team2":{"name":"Spirit","result":1},"matchId":"2352440","maxround":25},{"event":"IEM Winter 2021 Europe Closed Qualifier","time":"2021-10-19 01:49:19","team1":{"name":"9z","result":0},"team2":{"name":"Spirit","result":2},"matchId":"2352438","maxround":28},{"event":"IEM Winter 2021 Europe Closed Qualifier","time":"2021-10-18 23:24:45","team1":{"name":"K23","result":2},"team2":{"name":"Spirit","result":1},"matchId":"2352434","maxround":26},{"event":"IEM Winter 2021 Europe Closed Qualifier","time":"2021-10-18 22:38:34","team1":{"name":"ENCE","result":1},"team2":{"name":"FunPlus Phoenix","result":2},"matchId":"2352431","maxround":25},{"event":"IEM Winter 2021 Europe Closed Qualifier","time":"2021-10-18 21:20:56","team1":{"name":"fnatic","result":2},"team2":{"name":"Complexity","result":0},"matchId":"2352432","maxround":21},{"event":"BLAST Premier Fall Showdown 2021","time":"2021-10-18 02:39:18","team1":{"name":"MAD Lions","result":0},"team2":{"name":"Liquid","result":2},"matchId":"2351986","maxround":25},{"event":"BLAST Premier Fall Showdown 2021","time":"2021-10-15 23:46:40","team1":{"name":"Heroic","result":2},"team2":{"name":"Dignitas","result":0},"matchId":"2351981","maxround":36},{"event":"Pinnacle Fall Series 2","time":"2021-10-15 22:55:08","team1":{"name":"1WIN","result":0},"team2":{"name":"FunPlus Phoenix","result":2},"matchId":"2352090","maxround":25}]